ezsqlite/__init__.py
ezsqlite-2.0.0.dist-info/METADATA
ezsqlite-2.0.0.dist-info/WHEEL
ezsqlite-2.0.0.dist-info/top_level.txt
ezsqlite-2.0.0.dist-info/RECORD
